[
  {
    "Nome": "Hugo Marques",
    "ID": "39364",
    "Posição": "Guarda Redes",
    "Informações Pessoais": {
      "Nacionalidade": "AngolaDupla NacionalidadePortugalNaturalidadeBraga Outras LigaçõesParentescosTio de Renato SilvaPosiçãoGuarda RedesInternacionalizações A23 Jogos / 0 GolosInt Jovens2 Jogos / 0 GolosPé preferencialDireitoAltura192 cmPeso89 kgSituaçãoNo ativoClube atualPetro de LuandaHISTÓRICODFutebolÉPOCAEQUIPAJGAST2025/26Petro de Luanda80-2024/25Petro de Luanda34022023/24Petro de Luanda410-+35 registosEDIÇÕESEDIÇÃOJGASTCAN 2012---FIFA U17 World Cup 2003---TRANSFERÊNCIASÉpocaEquipaValor2022/2023Petro de LuandaCusto zero2021/2022Cape Town CityCusto zero2017/2018FarenseCusto zero2016/2017SC Covilhã-2014/2015Kabuscorp-2012/20131º de Agosto-2010/2011KabuscorpCusto zero2008/2009Tirsense (emp)-2007/2008Gil Vicente-2006/2007Vila Meã-2006/2007U. Lamas-2002/2003FC Porto-RAIO XJogador",
      "Altura": "192 cmPeso89 kgSituaçãoNo ativoClube atualPetro de LuandaHISTÓRICODFutebolÉPOCAEQUIPAJGAST2025/26Petro de Luanda80-2024/25Petro de Luanda34022023/24Petro de Luanda410-+35 registosEDIÇÕESEDIÇÃOJGASTCAN 2012---FIFA U17 World Cup 2003---TRANSFERÊNCIASÉpocaEquipaValor2022/2023Petro de LuandaCusto zero2021/2022Cape Town CityCusto zero2017/2018FarenseCusto zero2016/2017SC Covilhã-2014/2015Kabuscorp-2012/20131º de Agosto-2010/2011KabuscorpCusto zero2008/2009Tirsense (emp)-2007/2008Gil Vicente-2006/2007Vila Meã-2006/2007U. Lamas-2002/2003FC Porto-RAIO XJogador"
    },
    "Carreira Completa": [
      {
        "Época": "2025/26",
        "Equipa": "Petro de Luanda",
        "Formação": "",
        "Jogos": "8",
        "Golos": "0",
        "Assistências": "-"
      },
      {
        "Época": "2024/25",
        "Equipa": "Petro de Luanda",
        "Formação": "",
        "Jogos": "34",
        "Golos": "0",
        "Assistências": "2"
      },
      {
        "Época": "2023/24",
        "Equipa": "Petro de Luanda",
        "Formação": "",
        "Jogos": "41",
        "Golos": "0",
        "Assistências": "-"
      }
    ],
    "Carreira no Farense": []
  },
  {
    "Nome": "Beto Pimparel",
    "ID": "20355",
    "Posição": "Guarda Redes",
    "Informações Pessoais": {
      "Nacionalidade": "PortugalNaturalidadeLoures, LisboaOutras LigaçõesParentescosPai de Gonçalo Pimparel, Primo de Pedro Pimparel SerafimPosiçãoGuarda RedesInternacionalizações A16 Jogos / 0 GolosInt Jovens7 Jogos / 0 GolosPé preferencialDireitoAltura180 cmPeso76 kgEstreia como séniorEquipa:  SportingJogo: Louletano 2-2 SportingEdição: II Divisão B Zona Sul 00/01Treinador: Jean PaulÉpoca:  em 2000/01SituaçãoRetirado das competições oficiaisAgenteAntónio Teixeira - PromosportClube atualSem EquipaHISTÓRICODFutebolÉPOCAEQUIPAJGAST2022HIFK Helsinki120-2020/21Farense110-Leixões130-+39 registosFutebol de 6ÉPOCAEQUIPAJG2025/26Sporting [Fut.6  Legends]202024/25Sporting [Fut.6  Legends]--2023/24Sporting [Fut.6  Legends]--+39 registosEDIÇÕESEDIÇÃOJGASTRússia 2018---FIFA Confederations Cup 2017---Brasil 2014200Euro 2012---África do Sul 2010---Euro U21 2004---Toulon 2002---TRANSFERÊNCIASÉpocaEquipaValor2024/2025Sporting-2023/2024Sporting-2022Helsingfors IFKCusto zero2020/2021FarenseCusto zero2020/2021LeixõesCusto zero2017/2018GoztepeCusto zero2016/2017SportingCusto zero2013/2014Sevilla2.00 M €2012/2013Sevilla (emp)Custo zero2012/2013SC Braga (emp)Custo zero2011/2012CFR Cluj (emp)Custo zero2009/2010FC Porto400 mil €2006/2007LeixõesCusto zero2005/2006MarcoCusto zero2004/2005Chaves (emp)Custo zero2002/2003Casa Pia (emp)Custo zero1995/1996Sporting-RAIO XJogador",
      "Altura": "180 cmPeso76 kgEstreia como séniorEquipa:  SportingJogo: Louletano 2-2 SportingEdição: II Divisão B Zona Sul 00/01Treinador: Jean PaulÉpoca:  em 2000/01SituaçãoRetirado das competições oficiaisAgenteAntónio Teixeira - PromosportClube atualSem EquipaHISTÓRICODFutebolÉPOCAEQUIPAJGAST2022HIFK Helsinki120-2020/21Farense110-Leixões130-+39 registosFutebol de 6ÉPOCAEQUIPAJG2025/26Sporting [Fut.6  Legends]202024/25Sporting [Fut.6  Legends]--2023/24Sporting [Fut.6  Legends]--+39 registosEDIÇÕESEDIÇÃOJGASTRússia 2018---FIFA Confederations Cup 2017---Brasil 2014200Euro 2012---África do Sul 2010---Euro U21 2004---Toulon 2002---TRANSFERÊNCIASÉpocaEquipaValor2024/2025Sporting-2023/2024Sporting-2022Helsingfors IFKCusto zero2020/2021FarenseCusto zero2020/2021LeixõesCusto zero2017/2018GoztepeCusto zero2016/2017SportingCusto zero2013/2014Sevilla2.00 M €2012/2013Sevilla (emp)Custo zero2012/2013SC Braga (emp)Custo zero2011/2012CFR Cluj (emp)Custo zero2009/2010FC Porto400 mil €2006/2007LeixõesCusto zero2005/2006MarcoCusto zero2004/2005Chaves (emp)Custo zero2002/2003Casa Pia (emp)Custo zero1995/1996Sporting-RAIO XJogador"
    },
    "Carreira Completa": [
      {
        "Época": "2022",
        "Equipa": "HIFK Helsinki",
        "Formação": "",
        "Jogos": "12",
        "Golos": "0",
        "Assistências": "-"
      },
      {
        "Época": "2020/21",
        "Equipa": "Farense",
        "Formação": "",
        "Jogos": "11",
        "Golos": "0",
        "Assistências": "-"
      },
      {
        "Época": "",
        "Equipa": "Leixões",
        "Formação": "",
        "Jogos": "13",
        "Golos": "0",
        "Assistências": "-"
      }
    ],
    "Carreira no Farense": [
      {
        "Época": "2020/21",
        "Equipa": "Farense",
        "Formação": "",
        "Jogos": "11",
        "Golos": "0",
        "Assistências": "-"
      }
    ]
  },
  {
    "Nome": "Rafael Defendi",
    "ID": "42025",
    "Posição": "Guarda Redes",
    "Informações Pessoais": {
      "Nacionalidade": "BrasilDupla NacionalidadePortugalNaturalidadeRibeirão PretoOutras LigaçõesParentescosPrimo de Rodrigo Defendi, Primo de Márcio Defendi, Pai de António DefendiPosiçãoGuarda RedesInternacionalizações AInt JovensPé preferencialDireitoAltura191 cmPeso88 kgSituaçãoRetirado das competições oficiaisAgenteUltra SoccerClube atualSem EquipaHISTÓRICODFutebolÉPOCAEQUIPAJGAST2023/24Vila Meã170-2022/23Farense170-2021/22Farense240-+28 registosTRANSFERÊNCIASÉpocaEquipaValor2023/2024Vila Meã-2020/2021FarenseCusto zero2018/2019FC FamalicãoCusto zero2014/2015P. Ferreira-2013Bragantino-2012Monte Azul-2011PAEC-2010Bragantino-2009Mirassol-2009Sertãozinho-2008Grêmio Anápolis-2007/2008Desp. Aves-2007Grêmio Anápolis-2007Comercial-SP-HISTÓRICO COMO TREINADOREquipasÉPOCAEQUIPAJV2025/26FC Famalicão [S23]Treinador guarda-redes--2024/25FC Famalicão [S23]Treinador guarda-redes--+3 registosRAIO XJogador",
      "Altura": "191 cmPeso88 kgSituaçãoRetirado das competições oficiaisAgenteUltra SoccerClube atualSem EquipaHISTÓRICODFutebolÉPOCAEQUIPAJGAST2023/24Vila Meã170-2022/23Farense170-2021/22Farense240-+28 registosTRANSFERÊNCIASÉpocaEquipaValor2023/2024Vila Meã-2020/2021FarenseCusto zero2018/2019FC FamalicãoCusto zero2014/2015P. Ferreira-2013Bragantino-2012Monte Azul-2011PAEC-2010Bragantino-2009Mirassol-2009Sertãozinho-2008Grêmio Anápolis-2007/2008Desp. Aves-2007Grêmio Anápolis-2007Comercial-SP-HISTÓRICO COMO TREINADOREquipasÉPOCAEQUIPAJV2025/26FC Famalicão [S23]Treinador guarda-redes--2024/25FC Famalicão [S23]Treinador guarda-redes--+3 registosRAIO XJogador"
    },
    "Carreira Completa": [
      {
        "Época": "2023/24",
        "Equipa": "Vila Meã",
        "Formação": "",
        "Jogos": "17",
        "Golos": "0",
        "Assistências": "-"
      },
      {
        "Época": "2022/23",
        "Equipa": "Farense",
        "Formação": "",
        "Jogos": "17",
        "Golos": "0",
        "Assistências": "-"
      },
      {
        "Época": "2021/22",
        "Equipa": "Farense",
        "Formação": "",
        "Jogos": "24",
        "Golos": "0",
        "Assistências": "-"
      }
    ],
    "Carreira no Farense": [
      {
        "Época": "2022/23",
        "Equipa": "Farense",
        "Formação": "",
        "Jogos": "17",
        "Golos": "0",
        "Assistências": "-"
      },
      {
        "Época": "2021/22",
        "Equipa": "Farense",
        "Formação": "",
        "Jogos": "24",
        "Golos": "0",
        "Assistências": "-"
      }
    ]
  },
  {
    "Nome": "Ricardo Velho",
    "ID": "227413",
    "Posição": "Guarda Redes",
    "Informações Pessoais": {
      "Nacionalidade": "PortugalNaturalidadeVila Nova de FamalicãoOutras LigaçõesParentescosIrmão de Jorge Velho, Irmão de João VelhoPosiçãoGuarda RedesInternacionalizações AInt JovensPé preferencialDireitoAltura188 cmPeso90 kgSituaçãoNo ativoAgenteJorge Mendes (GestiFute)Clube atualGençlerbirligiContrato2028/06(Cláusula rescisão 20.0 milhões EUR)NOTÍCIASSeleção AAcom videoSelecionador abordou o lote de guardiões escolhido«Há alternativas para a baliza, não são sempre os mesmos»O técnico comentou a convocatória de Diogo Costa, Rui Silva e José Sá, «piscando o olho» a Ricardo Velho.Ricardo Velho deixa o Farense para rumar à Turquia12-09-2025 23:32E11mais notíciasHISTÓRICODFutebolÉPOCAEQUIPAJGAST2025/26Gençlerbirligi (E) [Farense]---Farense30-2024/25Farense300-+25 registosTRANSFERÊNCIASÉpocaEquipaValor2025/2026Gençlerbirligi (emp)-2020/2021Farense-2014/2015SC Braga-2013/2014Palmeiras FC-2012/2013SC Braga-2010/2011Trofense-2009/2010Salgueiros-2007/2008FC Porto-2006/2007V. Guimarães-2005/2006EF Fernando Pires-RAIO XJogador",
      "Altura": "188 cmPeso90 kgSituaçãoNo ativoAgenteJorge Mendes (GestiFute)Clube atualGençlerbirligiContrato2028/06(Cláusula rescisão 20.0 milhões EUR)NOTÍCIASSeleção AAcom videoSelecionador abordou o lote de guardiões escolhido«Há alternativas para a baliza, não são sempre os mesmos»O técnico comentou a convocatória de Diogo Costa, Rui Silva e José Sá, «piscando o olho» a Ricardo Velho.Ricardo Velho deixa o Farense para rumar à Turquia12-09-2025 23:32E11mais notíciasHISTÓRICODFutebolÉPOCAEQUIPAJGAST2025/26Gençlerbirligi (E) [Farense]---Farense30-2024/25Farense300-+25 registosTRANSFERÊNCIASÉpocaEquipaValor2025/2026Gençlerbirligi (emp)-2020/2021Farense-2014/2015SC Braga-2013/2014Palmeiras FC-2012/2013SC Braga-2010/2011Trofense-2009/2010Salgueiros-2007/2008FC Porto-2006/2007V. Guimarães-2005/2006EF Fernando Pires-RAIO XJogador"
    },
    "Carreira Completa": [
      {
        "Época": "2025/26",
        "Equipa": "Gençlerbirligi",
        "Formação": "",
        "Jogos": "-",
        "Golos": "-",
        "Assistências": "-"
      },
      {
        "Época": "",
        "Equipa": "Farense",
        "Formação": "",
        "Jogos": "3",
        "Golos": "0",
        "Assistências": "-"
      },
      {
        "Época": "2024/25",
        "Equipa": "Farense",
        "Formação": "",
        "Jogos": "30",
        "Golos": "0",
        "Assistências": "-"
      }
    ],
    "Carreira no Farense": [
      {
        "Época": "",
        "Equipa": "Farense",
        "Formação": "",
        "Jogos": "3",
        "Golos": "0",
        "Assistências": "-"
      },
      {
        "Época": "2024/25",
        "Equipa": "Farense",
        "Formação": "",
        "Jogos": "30",
        "Golos": "0",
        "Assistências": "-"
      }
    ]
  },
  {
    "Nome": "Ricardo Ferreira",
    "ID": "74740",
    "Posição": "Defesa",
    "Informações Pessoais": {
      "Nacionalidade": "CanadáDupla NacionalidadePortugalNaturalidadeMissisaugaOutras LigaçõesPosiçãoDefesa (Defesa Central)Internacionalizações A2 Jogos / 0 GolosInt Jovens14 Jogos / 1 GolosPé preferencialDireitoAltura190 cmPeso82 kgSituaçãoRetirado das competições oficiaisClube atualSem EquipaHISTÓRICODFutebolÉPOCAEQUIPAJGAST2020/21Farense10-2019/20B SAD50-2018/19SC Braga0--+16 registosTRANSFERÊNCIASÉpocaEquipaValor2020/2021Farense-2019/2020Belenenses SAD-2015/2016SC Braga-2014/2015P. Ferreira-2013/2014Olhanense-2012/2013Empoli-2011/2012Milan-RAIO XJogador",
      "Altura": "190 cmPeso82 kgSituaçãoRetirado das competições oficiaisClube atualSem EquipaHISTÓRICODFutebolÉPOCAEQUIPAJGAST2020/21Farense10-2019/20B SAD50-2018/19SC Braga0--+16 registosTRANSFERÊNCIASÉpocaEquipaValor2020/2021Farense-2019/2020Belenenses SAD-2015/2016SC Braga-2014/2015P. Ferreira-2013/2014Olhanense-2012/2013Empoli-2011/2012Milan-RAIO XJogador"
    },
    "Carreira Completa": [
      {
        "Época": "2020/21",
        "Equipa": "Farense",
        "Formação": "",
        "Jogos": "1",
        "Golos": "0",
        "Assistências": "-"
      },
      {
        "Época": "2019/20",
        "Equipa": "B SAD",
        "Formação": "",
        "Jogos": "5",
        "Golos": "0",
        "Assistências": "-"
      },
      {
        "Época": "2018/19",
        "Equipa": "SC Braga",
        "Formação": "",
        "Jogos": "0",
        "Golos": "-",
        "Assistências": "-"
      }
    ],
    "Carreira no Farense": [
      {
        "Época": "2020/21",
        "Equipa": "Farense",
        "Formação": "",
        "Jogos": "1",
        "Golos": "0",
        "Assistências": "-"
      }
    ]
  },
  {
    "Nome": "Alex Pinto",
    "ID": "413238",
    "Posição": "Defesa",
    "Informações Pessoais": {
      "Nacionalidade": "PortugalNaturalidadeGuimarãesOutras LigaçõesParentescosIrmão de Gonçalo PintoPosiçãoDefesa (Defesa Direito)Internacionalizações AInt Jovens9 Jogos / 0 GolosPé preferencialDireitoAltura187 cmPeso79 kgSituaçãoNo ativoClube atualFC AroucaContrato2026/06HISTÓRICODFutebolÉPOCAEQUIPAJGAST2025/26FC Arouca40-2024/25FC Arouca15012023/24Gil Vicente150-+26 registosTRANSFERÊNCIASÉpocaEquipaValor2024/2025FC AroucaCusto zero2023/2024Gil VicenteCusto zero2021/2022FC DAC 1904Custo zero2020/2021Farense-2019/2020Gil Vicente (emp)-2017/2018Benfica-2013/2014V. Guimarães-2011/2012Moreirense-2011/2012Os Sandinenses-RAIO XJogador",
      "Altura": "187 cmPeso79 kgSituaçãoNo ativoClube atualFC AroucaContrato2026/06HISTÓRICODFutebolÉPOCAEQUIPAJGAST2025/26FC Arouca40-2024/25FC Arouca15012023/24Gil Vicente150-+26 registosTRANSFERÊNCIASÉpocaEquipaValor2024/2025FC AroucaCusto zero2023/2024Gil VicenteCusto zero2021/2022FC DAC 1904Custo zero2020/2021Farense-2019/2020Gil Vicente (emp)-2017/2018Benfica-2013/2014V. Guimarães-2011/2012Moreirense-2011/2012Os Sandinenses-RAIO XJogador"
    },
    "Carreira Completa": [
      {
        "Época": "2025/26",
        "Equipa": "FC Arouca",
        "Formação": "",
        "Jogos": "4",
        "Golos": "0",
        "Assistências": "-"
      },
      {
        "Época": "2024/25",
        "Equipa": "FC Arouca",
        "Formação": "",
        "Jogos": "15",
        "Golos": "0",
        "Assistências": "1"
      },
      {
        "Época": "2023/24",
        "Equipa": "Gil Vicente",
        "Formação": "",
        "Jogos": "15",
        "Golos": "0",
        "Assistências": "-"
      }
    ],
    "Carreira no Farense": []
  },
  {
    "Nome": "Tomás Tavares",
    "ID": "413293",
    "Posição": "Defesa",
    "Informações Pessoais": {
      "Nacionalidade": "PortugalDupla NacionalidadeCabo VerdeNaturalidadeLisboaOutras LigaçõesParentescosPrimo de Martim Santos, Filho de TavaresPosiçãoDefesa (Defesa Direito)Internacionalizações AInt Jovens47 Jogos / 0 GolosPé preferencialDireitoAltura184 cmPeso69 kgSituaçãoNo ativoAgentePedro Traquino (Traquifoot)Clube atualWisla PlockContrato2026/06HISTÓRICODFutebolÉPOCAEQUIPAJGAST2025/26Wisla Plock50-2024/25AFS1201LASK Linz (E) [Spartak Moskva]40-+24 registosEDIÇÕESEDIÇÃOJGASTEuro U21 2021100Toulon 2019301Euro U19 2019501Euro U17 2018300TRANSFERÊNCIASÉpocaEquipaValor2025/2026Wisla PlockCusto zero2024/2025AFSCusto zero2024/2025LASK Linz (emp)Custo zero2022/2023Spartak Moskva2.00 M €2021/2022FC Basel (emp)Custo zero2020/2021Farense (emp)Custo zero2020/2021Alavés (emp)Custo zeroRAIO XJogador",
      "Altura": "184 cmPeso69 kgSituaçãoNo ativoAgentePedro Traquino (Traquifoot)Clube atualWisla PlockContrato2026/06HISTÓRICODFutebolÉPOCAEQUIPAJGAST2025/26Wisla Plock50-2024/25AFS1201LASK Linz (E) [Spartak Moskva]40-+24 registosEDIÇÕESEDIÇÃOJGASTEuro U21 2021100Toulon 2019301Euro U19 2019501Euro U17 2018300TRANSFERÊNCIASÉpocaEquipaValor2025/2026Wisla PlockCusto zero2024/2025AFSCusto zero2024/2025LASK Linz (emp)Custo zero2022/2023Spartak Moskva2.00 M €2021/2022FC Basel (emp)Custo zero2020/2021Farense (emp)Custo zero2020/2021Alavés (emp)Custo zeroRAIO XJogador"
    },
    "Carreira Completa": [
      {
        "Época": "2025/26",
        "Equipa": "Wisla Plock",
        "Formação": "",
        "Jogos": "5",
        "Golos": "0",
        "Assistências": "-"
      },
      {
        "Época": "2024/25",
        "Equipa": "AFS",
        "Formação": "",
        "Jogos": "12",
        "Golos": "0",
        "Assistências": "1"
      },
      {
        "Época": "",
        "Equipa": "LASK Linz",
        "Formação": "",
        "Jogos": "4",
        "Golos": "0",
        "Assistências": "-"
      }
    ],
    "Carreira no Farense": []
  },
  {
    "Nome": "César Martins",
    "ID": "248038",
    "Posição": "Defesa",
    "Informações Pessoais": {
      "Nacionalidade": "BrasilNaturalidadeMairinque (SP)Outras LigaçõesPosiçãoDefesa (Defesa Central)Internacionalizações AInt JovensPé preferencialDireitoAltura190 cmPeso77 kgSituaçãoNo ativoClube atualGrêmio NovorizontinoHISTÓRICODFutebolÉPOCAEQUIPAJGAST2025Grêmio Novorizontino32122024Grêmio Novorizontino152-2023Grêmio Novorizontino315-+22 registosTRANSFERÊNCIASÉpocaEquipaValor2023Grêmio Novorizontino-2021BolívarCusto zero2020/2021FarenseCusto zero2018/2019Santa ClaraCusto zero2018Juventude (emp)-2017/2018V. Setúbal (emp)-2016/2017Nacional (emp)-2016Flamengo (emp)-2015Flamengo (emp)-2014/2015Benfica-2014Ponte Preta-2013Ponte Preta (emp)-RAIO XJogador",
      "Altura": "190 cmPeso77 kgSituaçãoNo ativoClube atualGrêmio NovorizontinoHISTÓRICODFutebolÉPOCAEQUIPAJGAST2025Grêmio Novorizontino32122024Grêmio Novorizontino152-2023Grêmio Novorizontino315-+22 registosTRANSFERÊNCIASÉpocaEquipaValor2023Grêmio Novorizontino-2021BolívarCusto zero2020/2021FarenseCusto zero2018/2019Santa ClaraCusto zero2018Juventude (emp)-2017/2018V. Setúbal (emp)-2016/2017Nacional (emp)-2016Flamengo (emp)-2015Flamengo (emp)-2014/2015Benfica-2014Ponte Preta-2013Ponte Preta (emp)-RAIO XJogador"
    },
    "Carreira Completa": [
      {
        "Época": "2025",
        "Equipa": "Grêmio Novorizontino",
        "Formação": "",
        "Jogos": "32",
        "Golos": "1",
        "Assistências": "2"
      },
      {
        "Época": "2024",
        "Equipa": "Grêmio Novorizontino",
        "Formação": "",
        "Jogos": "15",
        "Golos": "2",
        "Assistências": "-"
      },
      {
        "Época": "2023",
        "Equipa": "Grêmio Novorizontino",
        "Formação": "",
        "Jogos": "31",
        "Golos": "5",
        "Assistências": "-"
      }
    ],
    "Carreira no Farense": []
  },
  {
    "Nome": "André Pinto",
    "ID": "46702",
    "Posição": "Defesa",
    "Informações Pessoais": {
      "Nacionalidade": "PortugalNaturalidadeVila Nova de GaiaOutras LigaçõesParentescosPrimo de Vasco PintoPosiçãoDefesa (Defesa Central)Internacionalizações A1 Jogos / 0 GolosInt Jovens28 Jogos / 0 GolosPé preferencialDireitoAltura194 cmPeso84 kgSituaçãoRetirado das competições oficiaisAgentePPSportsClube atualSem EquipaHISTÓRICODFutebolÉPOCAEQUIPAJGAST2021/22Dinamo Bucuresti90-2020/21Farense121-2019/20Al-Fateh1401+27 registosEDIÇÕESEDIÇÃOJGASTToulon 2009200TRANSFERÊNCIASÉpocaEquipaValor2021/2022Dinamo Bucuresti-2020/2021Farense-2019/2020Al Fateh-2017/2018Sporting-2013/2014SC Braga-2012/2013Panathinaikos-2011/2012Olhanense (emp)-2010/2011Portimonense (emp)-2009/2010V. Setúbal (emp)-2008/2009Santa Clara (emp)-2004/2005Padroense (emp)-1999/2000FC Porto-HISTÓRICO COMO TREINADOREquipasÉPOCAEQUIPAJV2025/26SC Braga [B]Treinador-adjunto--2024/25SC Braga [Jun.B S17]Treinador-adjunto--2023/24Gil Vicente [Jun.A S19]Treinador-adjunto--+4 registosRAIO XJogador",
      "Altura": "194 cmPeso84 kgSituaçãoRetirado das competições oficiaisAgentePPSportsClube atualSem EquipaHISTÓRICODFutebolÉPOCAEQUIPAJGAST2021/22Dinamo Bucuresti90-2020/21Farense121-2019/20Al-Fateh1401+27 registosEDIÇÕESEDIÇÃOJGASTToulon 2009200TRANSFERÊNCIASÉpocaEquipaValor2021/2022Dinamo Bucuresti-2020/2021Farense-2019/2020Al Fateh-2017/2018Sporting-2013/2014SC Braga-2012/2013Panathinaikos-2011/2012Olhanense (emp)-2010/2011Portimonense (emp)-2009/2010V. Setúbal (emp)-2008/2009Santa Clara (emp)-2004/2005Padroense (emp)-1999/2000FC Porto-HISTÓRICO COMO TREINADOREquipasÉPOCAEQUIPAJV2025/26SC Braga [B]Treinador-adjunto--2024/25SC Braga [Jun.B S17]Treinador-adjunto--2023/24Gil Vicente [Jun.A S19]Treinador-adjunto--+4 registosRAIO XJogador"
    },
    "Carreira Completa": [
      {
        "Época": "2021/22",
        "Equipa": "Dinamo Bucuresti",
        "Formação": "",
        "Jogos": "9",
        "Golos": "0",
        "Assistências": "-"
      },
      {
        "Época": "2020/21",
        "Equipa": "Farense",
        "Formação": "",
        "Jogos": "12",
        "Golos": "1",
        "Assistências": "-"
      },
      {
        "Época": "2019/20",
        "Equipa": "Al-Fateh",
        "Formação": "",
        "Jogos": "14",
        "Golos": "0",
        "Assistências": "1"
      }
    ],
    "Carreira no Farense": [
      {
        "Época": "2020/21",
        "Equipa": "Farense",
        "Formação": "",
        "Jogos": "12",
        "Golos": "1",
        "Assistências": "-"
      }
    ]
  },
  {
    "Nome": "Cássio Scheid",
    "ID": "454744",
    "Posição": "Defesa",
    "Informações Pessoais": {
      "Nacionalidade": "BrasilOutras LigaçõesPosiçãoDefesaInternacionalizações AInt JovensPé preferencialEsquerdoAltura186 cmPeso81 kgSituaçãoNo ativoClube atualDewa UnitedHISTÓRICODFutebolÉPOCAEQUIPAJGAST2025/26Dewa United30-2024/25Da Nang101-Malut United141-+24 registosTRANSFERÊNCIASÉpocaEquipaValor2025/2026Dewa United-2024/2025Da Nang-2024/2025Malut United-2023/2024FC Ararat-Armenia-2021/2022BG Pathum UnitedCusto zero2021/2022VarzimCusto zero2016/2017Farense-2016São Carlos-2015Juventus-SP-2014União São João-2014Juventus-SP-RAIO XJogador",
      "Altura": "186 cmPeso81 kgSituaçãoNo ativoClube atualDewa UnitedHISTÓRICODFutebolÉPOCAEQUIPAJGAST2025/26Dewa United30-2024/25Da Nang101-Malut United141-+24 registosTRANSFERÊNCIASÉpocaEquipaValor2025/2026Dewa United-2024/2025Da Nang-2024/2025Malut United-2023/2024FC Ararat-Armenia-2021/2022BG Pathum UnitedCusto zero2021/2022VarzimCusto zero2016/2017Farense-2016São Carlos-2015Juventus-SP-2014União São João-2014Juventus-SP-RAIO XJogador"
    },
    "Carreira Completa": [
      {
        "Época": "2025/26",
        "Equipa": "Dewa United",
        "Formação": "",
        "Jogos": "3",
        "Golos": "0",
        "Assistências": "-"
      },
      {
        "Época": "2024/25",
        "Equipa": "Da Nang",
        "Formação": "",
        "Jogos": "10",
        "Golos": "1",
        "Assistências": "-"
      },
      {
        "Época": "",
        "Equipa": "Malut United",
        "Formação": "",
        "Jogos": "14",
        "Golos": "1",
        "Assistências": "-"
      }
    ],
    "Carreira no Farense": []
  },
  {
    "Nome": "Eduardo Mancha",
    "ID": "461880",
    "Posição": "Defesa",
    "Informações Pessoais": {
      "Nacionalidade": "BrasilOutras LigaçõesPosiçãoDefesa (Defesa Central)Internacionalizações AInt JovensPé preferencialEsquerdoAltura187 cmPeso80 kgSituaçãoNo ativoClube atualVentforet KofuHISTÓRICODFutebolÉPOCAEQUIPAJGAST2025Ventforet Kofu28442024Ventforet Kofu133-2023Ventforet Kofu342-+14 registosTRANSFERÊNCIASÉpocaEquipaValor2022Ventforet KofuCusto zero2020/2021Farense-2019/2020Machine Sazi-2018/2019Birkirkara-2017Guarani-MG-2016Jabaquara-RAIO XJogador",
      "Altura": "187 cmPeso80 kgSituaçãoNo ativoClube atualVentforet KofuHISTÓRICODFutebolÉPOCAEQUIPAJGAST2025Ventforet Kofu28442024Ventforet Kofu133-2023Ventforet Kofu342-+14 registosTRANSFERÊNCIASÉpocaEquipaValor2022Ventforet KofuCusto zero2020/2021Farense-2019/2020Machine Sazi-2018/2019Birkirkara-2017Guarani-MG-2016Jabaquara-RAIO XJogador"
    },
    "Carreira Completa": [
      {
        "Época": "2025",
        "Equipa": "Ventforet Kofu",
        "Formação": "",
        "Jogos": "28",
        "Golos": "4",
        "Assistências": "4"
      },
      {
        "Época": "2024",
        "Equipa": "Ventforet Kofu",
        "Formação": "",
        "Jogos": "13",
        "Golos": "3",
        "Assistências": "-"
      },
      {
        "Época": "2023",
        "Equipa": "Ventforet Kofu",
        "Formação": "",
        "Jogos": "34",
        "Golos": "2",
        "Assistências": "-"
      }
    ],
    "Carreira no Farense": []
  },
  {
    "Nome": "Abner Felipe",
    "ID": "349062",
    "Posição": "Defesa",
    "Informações Pessoais": {
      "Nacionalidade": "BrasilDupla NacionalidadeEspanhaNaturalidadeLondrina (PR)Outras LigaçõesPosiçãoDefesa (Defesa Esquerdo)Internacionalizações AInt Jovens7 Jogos / 0 GolosPé preferencialEsquerdoAltura180 cmPeso73 kgSituaçãoNo ativoAgenteLeonardo CornaciniClube atualUSL DunkerqueHISTÓRICODFutebolÉPOCAEQUIPAJGAST2025/26USL Dunkerque110-2024/25USL Dunkerque33032023/24RWDM Brussels290-+22 registosEDIÇÕESEDIÇÃOJGASTWC U17 2013300Toulon 2013400TRANSFERÊNCIASÉpocaEquipaValor2024/2025USL Dunkerque-2023/2024RWDM Brussels-2020/2021Farense-2020EC Água Santa (emp)-2019Athletico Paranaense (emp)-2019Athletico Paranaense (emp)-2018Coritiba (emp)-2018Coritiba (emp)-2017/2018Estoril Praia (emp)-2016/2017Real Madrid (emp)-2015/2016Real Madrid (emp)-2014/2015Real Madrid (emp)-2014/2015Real Madrid (emp)-2014PSTC-RAIO XJogador",
      "Altura": "180 cmPeso73 kgSituaçãoNo ativoAgenteLeonardo CornaciniClube atualUSL DunkerqueHISTÓRICODFutebolÉPOCAEQUIPAJGAST2025/26USL Dunkerque110-2024/25USL Dunkerque33032023/24RWDM Brussels290-+22 registosEDIÇÕESEDIÇÃOJGASTWC U17 2013300Toulon 2013400TRANSFERÊNCIASÉpocaEquipaValor2024/2025USL Dunkerque-2023/2024RWDM Brussels-2020/2021Farense-2020EC Água Santa (emp)-2019Athletico Paranaense (emp)-2019Athletico Paranaense (emp)-2018Coritiba (emp)-2018Coritiba (emp)-2017/2018Estoril Praia (emp)-2016/2017Real Madrid (emp)-2015/2016Real Madrid (emp)-2014/2015Real Madrid (emp)-2014/2015Real Madrid (emp)-2014PSTC-RAIO XJogador"
    },
    "Carreira Completa": [
      {
        "Época": "2025/26",
        "Equipa": "USL Dunkerque",
        "Formação": "",
        "Jogos": "11",
        "Golos": "0",
        "Assistências": "-"
      },
      {
        "Época": "2024/25",
        "Equipa": "USL Dunkerque",
        "Formação": "",
        "Jogos": "33",
        "Golos": "0",
        "Assistências": "3"
      },
      {
        "Época": "2023/24",
        "Equipa": "RWDM Brussels",
        "Formação": "",
        "Jogos": "29",
        "Golos": "0",
        "Assistências": "-"
      }
    ],
    "Carreira no Farense": []
  },
  {
    "Nome": "Fábio Nunes",
    "ID": "160496",
    "Posição": "Defesa",
    "Informações Pessoais": {
      "Nacionalidade": "PortugalNaturalidadePortimãoOutras LigaçõesPosiçãoDefesa (Defesa Esquerdo)Internacionalizações AInt Jovens26 Jogos / 4 GolosPé preferencialEsquerdoAltura185 cmPeso78 kgSituaçãoNo ativoClube atualPortimonenseHISTÓRICODFutebolÉPOCAEQUIPAJGAST2025/26Portimonense (Clube)---2024/25Widzew Lodz70-2023/24Widzew Lodz3744+33 registosTRANSFERÊNCIASÉpocaEquipaValor2025/2026Portimonense (Clube)-2021/2022Widzew LodzCusto zero2018/2019Farense-2017/2018Kerkyra-2016/2017Belenenses-2016/2017Tondela-2014/2015Belenenses-2013/2014LatinaCusto zero2012/2013Blackburn -2011/2012Parma (emp)-2010/2011FC Porto (emp)-2006/2007Portimonense-2005/2006Benfica-2001/2002Portimonense-RAIO XJogador",
      "Altura": "185 cmPeso78 kgSituaçãoNo ativoClube atualPortimonenseHISTÓRICODFutebolÉPOCAEQUIPAJGAST2025/26Portimonense (Clube)---2024/25Widzew Lodz70-2023/24Widzew Lodz3744+33 registosTRANSFERÊNCIASÉpocaEquipaValor2025/2026Portimonense (Clube)-2021/2022Widzew LodzCusto zero2018/2019Farense-2017/2018Kerkyra-2016/2017Belenenses-2016/2017Tondela-2014/2015Belenenses-2013/2014LatinaCusto zero2012/2013Blackburn -2011/2012Parma (emp)-2010/2011FC Porto (emp)-2006/2007Portimonense-2005/2006Benfica-2001/2002Portimonense-RAIO XJogador"
    },
    "Carreira Completa": [
      {
        "Época": "2025/26",
        "Equipa": "Portimonense (Clube)",
        "Formação": "",
        "Jogos": "-",
        "Golos": "-",
        "Assistências": "-"
      },
      {
        "Época": "2024/25",
        "Equipa": "Widzew Lodz",
        "Formação": "",
        "Jogos": "7",
        "Golos": "0",
        "Assistências": "-"
      },
      {
        "Época": "2023/24",
        "Equipa": "Widzew Lodz",
        "Formação": "",
        "Jogos": "37",
        "Golos": "4",
        "Assistências": "4"
      }
    ],
    "Carreira no Farense": []
  },
  {
    "Nome": "Pedro Simões",
    "ID": "473411",
    "Posição": "Médio",
    "Informações Pessoais": {
      "Nacionalidade": "PortugalOutras LigaçõesPosiçãoMédio (Médio Centro)Internacionalizações AInt JovensPé preferencialEsquerdoAltura181 cmPeso77 kgSituaçãoNo ativoClube atualGD LagoaHISTÓRICODFutebolÉPOCAEQUIPAJGAST2025/26GD Lagoa81-2024/25GD Lagoa242-2023/24GD Lagoa3018-+22 registosTRANSFERÊNCIASÉpocaEquipaValor2023/2024GD Lagoa-2021/2022Esp. Lagos-2020/2021Louletano (emp)-2019/2020Esp. Lagos (emp)-2017/2018Farense-2015/2016Portimonense-2012/2013Imortal DC-2011/2012Odiáxere-RAIO XJogador",
      "Altura": "181 cmPeso77 kgSituaçãoNo ativoClube atualGD LagoaHISTÓRICODFutebolÉPOCAEQUIPAJGAST2025/26GD Lagoa81-2024/25GD Lagoa242-2023/24GD Lagoa3018-+22 registosTRANSFERÊNCIASÉpocaEquipaValor2023/2024GD Lagoa-2021/2022Esp. Lagos-2020/2021Louletano (emp)-2019/2020Esp. Lagos (emp)-2017/2018Farense-2015/2016Portimonense-2012/2013Imortal DC-2011/2012Odiáxere-RAIO XJogador"
    },
    "Carreira Completa": [
      {
        "Época": "2025/26",
        "Equipa": "GD Lagoa",
        "Formação": "",
        "Jogos": "8",
        "Golos": "1",
        "Assistências": "-"
      },
      {
        "Época": "2024/25",
        "Equipa": "GD Lagoa",
        "Formação": "",
        "Jogos": "24",
        "Golos": "2",
        "Assistências": "-"
      },
      {
        "Época": "2023/24",
        "Equipa": "GD Lagoa",
        "Formação": "",
        "Jogos": "30",
        "Golos": "18",
        "Assistências": "-"
      }
    ],
    "Carreira no Farense": []
  },
  {
    "Nome": "Miguel Bandarra",
    "ID": "247828",
    "Posição": "Médio",
    "Informações Pessoais": {
      "Nacionalidade": "PortugalNaturalidadeVila Real de Santo AntónioOutras LigaçõesPosiçãoDefesa (Defesa Direito)Internacionalizações AInt JovensPé preferencialDireitoAltura182 cmPeso76 kgSituaçãoNo ativoAgenteIdoloásis FutebolClube atualBelenensesHISTÓRICODFutebolÉPOCAEQUIPAJGAST2025/26Belenenses11002024/25Académico15212023/24Académico3403+28 registosTRANSFERÊNCIASÉpocaEquipaValor2025/2026Belenenses-2023/2024Académico de Viseu-2019/2020FarenseCusto zero2018/2019Casa Pia-2017/2018Armacenenses-2016/2017Louletano-2015/2016Lusitano VRSA-2015/2016Pedras Salgadas-2014/2015Lusitano VRSA-2013/2014Olhanense-2012/2013Lusitano VRSA-2011/2012Sporting-2006/2007Lusitano VRSA-2005/2006CN Guadiana-2005/2006Lusitano VRSA-RAIO XJogador",
      "Altura": "182 cmPeso76 kgSituaçãoNo ativoAgenteIdoloásis FutebolClube atualBelenensesHISTÓRICODFutebolÉPOCAEQUIPAJGAST2025/26Belenenses11002024/25Académico15212023/24Académico3403+28 registosTRANSFERÊNCIASÉpocaEquipaValor2025/2026Belenenses-2023/2024Académico de Viseu-2019/2020FarenseCusto zero2018/2019Casa Pia-2017/2018Armacenenses-2016/2017Louletano-2015/2016Lusitano VRSA-2015/2016Pedras Salgadas-2014/2015Lusitano VRSA-2013/2014Olhanense-2012/2013Lusitano VRSA-2011/2012Sporting-2006/2007Lusitano VRSA-2005/2006CN Guadiana-2005/2006Lusitano VRSA-RAIO XJogador"
    },
    "Carreira Completa": [
      {
        "Época": "2025/26",
        "Equipa": "Belenenses",
        "Formação": "",
        "Jogos": "11",
        "Golos": "0",
        "Assistências": "0"
      },
      {
        "Época": "2024/25",
        "Equipa": "Académico",
        "Formação": "",
        "Jogos": "15",
        "Golos": "2",
        "Assistências": "1"
      },
      {
        "Época": "2023/24",
        "Equipa": "Académico",
        "Formação": "",
        "Jogos": "34",
        "Golos": "0",
        "Assistências": "3"
      }
    ],
    "Carreira no Farense": []
  },
  {
    "Nome": "Filipe Melo",
    "ID": "84949",
    "Posição": "Médio",
    "Informações Pessoais": {
      "Nacionalidade": "PortugalNaturalidadeSanta Maria de LamasOutras LigaçõesPosiçãoMédio (Médio Defensivo)Internacionalizações AInt JovensPé preferencialDireitoAltura189 cmPeso84 kgSituaçãoNo ativoAgenteClube atualU. LamasHISTÓRICODFutebolÉPOCAEQUIPAJGAST2025/26U. Lamas40-2024/25U. Lamas120-2023/24U. Lamas353-+34 registosTRANSFERÊNCIASÉpocaEquipaValor2022/2023U. Lamas-2021/2022Vilafranquense-2019/2020Farense-2017/2018Chaves-2016/2017Paços Ferreira (emp)-2014/2015Sheffield Wed.700 mil €2013/2014Moreirense-2012/2013Naval-2011/2012Arouca (emp)-2010/2011Sp. Espinho (emp)-2009/2010Avanca (emp)-2009/2010Beira-Mar-RAIO XJogador",
      "Altura": "189 cmPeso84 kgSituaçãoNo ativoAgenteClube atualU. LamasHISTÓRICODFutebolÉPOCAEQUIPAJGAST2025/26U. Lamas40-2024/25U. Lamas120-2023/24U. Lamas353-+34 registosTRANSFERÊNCIASÉpocaEquipaValor2022/2023U. Lamas-2021/2022Vilafranquense-2019/2020Farense-2017/2018Chaves-2016/2017Paços Ferreira (emp)-2014/2015Sheffield Wed.700 mil €2013/2014Moreirense-2012/2013Naval-2011/2012Arouca (emp)-2010/2011Sp. Espinho (emp)-2009/2010Avanca (emp)-2009/2010Beira-Mar-RAIO XJogador"
    },
    "Carreira Completa": [
      {
        "Época": "2025/26",
        "Equipa": "U. Lamas",
        "Formação": "",
        "Jogos": "4",
        "Golos": "0",
        "Assistências": "-"
      },
      {
        "Época": "2024/25",
        "Equipa": "U. Lamas",
        "Formação": "",
        "Jogos": "12",
        "Golos": "0",
        "Assistências": "-"
      },
      {
        "Época": "2023/24",
        "Equipa": "U. Lamas",
        "Formação": "",
        "Jogos": "35",
        "Golos": "3",
        "Assistências": "-"
      }
    ],
    "Carreira no Farense": []
  },
  {
    "Nome": "Bura",
    "ID": "554773",
    "Posição": "Médio",
    "Informações Pessoais": {
      "Nacionalidade": "Guiné-BissauNaturalidadeBissauOutras LigaçõesPosiçãoMédio (Médio Defensivo) / Defesa (Defesa Central)Internacionalizações A37 Jogos / 2 GolosInt JovensPé preferencialDireitoAltura184 cmPeso76 kgSituaçãoNo ativoClube atualCosta do SolHISTÓRICODFutebolÉPOCAEQUIPAJGAST2025Costa do Sol182-2024San Antonio FC22112022/23Mes Kerman180-+13 registosEDIÇÕESEDIÇÃOJGASTCAN 2021300CAN 2019200TRANSFERÊNCIASÉpocaEquipaValor2025Costa do Sol-2024San Antonio FC-2022/2023Mes KermanCusto zero2019/2020Farense-2018/2019Desp. Aves (emp)-2018/2019Desp. Aves (emp)-2017/2018Oriental-2016/2017Os Vilanovenses-2015/2016Bissau e Benfica-RAIO XJogador",
      "Altura": "184 cmPeso76 kgSituaçãoNo ativoClube atualCosta do SolHISTÓRICODFutebolÉPOCAEQUIPAJGAST2025Costa do Sol182-2024San Antonio FC22112022/23Mes Kerman180-+13 registosEDIÇÕESEDIÇÃOJGASTCAN 2021300CAN 2019200TRANSFERÊNCIASÉpocaEquipaValor2025Costa do Sol-2024San Antonio FC-2022/2023Mes KermanCusto zero2019/2020Farense-2018/2019Desp. Aves (emp)-2018/2019Desp. Aves (emp)-2017/2018Oriental-2016/2017Os Vilanovenses-2015/2016Bissau e Benfica-RAIO XJogador"
    },
    "Carreira Completa": [
      {
        "Época": "2025",
        "Equipa": "Costa do Sol",
        "Formação": "",
        "Jogos": "18",
        "Golos": "2",
        "Assistências": "-"
      },
      {
        "Época": "2024",
        "Equipa": "San Antonio FC",
        "Formação": "",
        "Jogos": "22",
        "Golos": "1",
        "Assistências": "1"
      },
      {
        "Época": "2022/23",
        "Equipa": "Mes Kerman",
        "Formação": "",
        "Jogos": "18",
        "Golos": "0",
        "Assistências": "-"
      }
    ],
    "Carreira no Farense": []
  },
  {
    "Nome": "Fabrício Isidoro",
    "ID": "133046",
    "Posição": "Médio",
    "Informações Pessoais": {
      "Nacionalidade": "BrasilNaturalidadeBelo HorizonteOutras LigaçõesParentescosFilho de Paulo IsidoroPosiçãoMédio (Médio Centro)Internacionalizações AInt JovensPé preferencialDireitoAltura172 cmPeso64 kgSituaçãoNo ativoClube atualAthletic-MGHISTÓRICODFutebolÉPOCAEQUIPAJGAST2025Athletic-MG170-Leixões70-Al-Muharraq---+29 registosTRANSFERÊNCIASÉpocaEquipaValor2025Athletic-MG-2024/2025LeixõesCusto zero2024/2025Al-MuharraqCusto zero2017/2018Farense-2016/2017Louletano-2015Formiga-2014Caldas Novas-2014Tupi-2013Villa Nova-2013Sertãozinho-2012Democrata-SL-2012Poços de Caldas-2008Itaúna (emp)-RAIO XJogador",
      "Altura": "172 cmPeso64 kgSituaçãoNo ativoClube atualAthletic-MGHISTÓRICODFutebolÉPOCAEQUIPAJGAST2025Athletic-MG170-Leixões70-Al-Muharraq---+29 registosTRANSFERÊNCIASÉpocaEquipaValor2025Athletic-MG-2024/2025LeixõesCusto zero2024/2025Al-MuharraqCusto zero2017/2018Farense-2016/2017Louletano-2015Formiga-2014Caldas Novas-2014Tupi-2013Villa Nova-2013Sertãozinho-2012Democrata-SL-2012Poços de Caldas-2008Itaúna (emp)-RAIO XJogador"
    },
    "Carreira Completa": [
      {
        "Época": "2025",
        "Equipa": "Athletic-MG",
        "Formação": "",
        "Jogos": "17",
        "Golos": "0",
        "Assistências": "-"
      },
      {
        "Época": "",
        "Equipa": "Leixões",
        "Formação": "",
        "Jogos": "7",
        "Golos": "0",
        "Assistências": "-"
      },
      {
        "Época": "",
        "Equipa": "Al-Muharraq",
        "Formação": "",
        "Jogos": "-",
        "Golos": "-",
        "Assistências": "-"
      }
    ],
    "Carreira no Farense": []
  },
  {
    "Nome": "Cláudio Falcão",
    "ID": "391764",
    "Posição": "Médio",
    "Informações Pessoais": {
      "Nacionalidade": "BrasilNaturalidadeAquidauanaOutras LigaçõesPosiçãoMédio (Médio Defensivo)Internacionalizações AInt JovensPé preferencialDireitoAltura187 cmPeso77 kgSituaçãoNo ativoClube atualFarenseContrato2029/06HISTÓRICODFutebolÉPOCAEQUIPAJGAST2025/26Farense91-2024/25Farense35122023/24Farense3541+18 registosTRANSFERÊNCIASÉpocaEquipaValor2020/2021Farense-2016/2017Desp. Aves-2015Independente de Limeira -RAIO XJogador",
      "Altura": "187 cmPeso77 kgSituaçãoNo ativoClube atualFarenseContrato2029/06HISTÓRICODFutebolÉPOCAEQUIPAJGAST2025/26Farense91-2024/25Farense35122023/24Farense3541+18 registosTRANSFERÊNCIASÉpocaEquipaValor2020/2021Farense-2016/2017Desp. Aves-2015Independente de Limeira -RAIO XJogador"
    },
    "Carreira Completa": [
      {
        "Época": "2025/26",
        "Equipa": "Farense",
        "Formação": "",
        "Jogos": "9",
        "Golos": "1",
        "Assistências": "-"
      },
      {
        "Época": "2024/25",
        "Equipa": "Farense",
        "Formação": "",
        "Jogos": "35",
        "Golos": "1",
        "Assistências": "2"
      },
      {
        "Época": "2023/24",
        "Equipa": "Farense",
        "Formação": "",
        "Jogos": "35",
        "Golos": "4",
        "Assistências": "1"
      }
    ],
    "Carreira no Farense": [
      {
        "Época": "2025/26",
        "Equipa": "Farense",
        "Formação": "",
        "Jogos": "9",
        "Golos": "1",
        "Assistências": "-"
      },
      {
        "Época": "2024/25",
        "Equipa": "Farense",
        "Formação": "",
        "Jogos": "35",
        "Golos": "1",
        "Assistências": "2"
      },
      {
        "Época": "2023/24",
        "Equipa": "Farense",
        "Formação": "",
        "Jogos": "35",
        "Golos": "4",
        "Assistências": "1"
      }
    ]
  },
  {
    "Nome": "Jonatan Lucca",
    "ID": "267766",
    "Posição": "Médio",
    "Informações Pessoais": {
      "Nacionalidade": "BrasilDupla NacionalidadeItáliaNaturalidade Santa MariaOutras LigaçõesParentescosIrmão de Cristian LuccaPosiçãoMédio (Médio Defensivo)Internacionalizações AInt JovensPé preferencialEsquerdoAltura184 cmPeso77 kgSituaçãoNo ativoClube atualPakhtakorHISTÓRICODFutebolÉPOCAEQUIPAJGAST2025Pakhtakor120-AFS100-2023/24AFS2831+23 registosTRANSFERÊNCIASÉpocaEquipaValor2025PakhtakorCusto zero2023/2024AVSCusto zero2022StabaekCusto zero2019/2020FarenseCusto zero2018/2019Belenenses-2016/2017Pune City-2015/2016Kelantan FA (emp)-2015/2016FC Goa (emp)-2015Guaratinguetá (emp)-2015Atlético Paranaense-2014Atlético Paranaense (emp)-2012/2013Roma700 mil €RAIO XJogador",
      "Altura": "184 cmPeso77 kgSituaçãoNo ativoClube atualPakhtakorHISTÓRICODFutebolÉPOCAEQUIPAJGAST2025Pakhtakor120-AFS100-2023/24AFS2831+23 registosTRANSFERÊNCIASÉpocaEquipaValor2025PakhtakorCusto zero2023/2024AVSCusto zero2022StabaekCusto zero2019/2020FarenseCusto zero2018/2019Belenenses-2016/2017Pune City-2015/2016Kelantan FA (emp)-2015/2016FC Goa (emp)-2015Guaratinguetá (emp)-2015Atlético Paranaense-2014Atlético Paranaense (emp)-2012/2013Roma700 mil €RAIO XJogador"
    },
    "Carreira Completa": [
      {
        "Época": "2025",
        "Equipa": "Pakhtakor",
        "Formação": "",
        "Jogos": "12",
        "Golos": "0",
        "Assistências": "-"
      },
      {
        "Época": "",
        "Equipa": "AFS",
        "Formação": "",
        "Jogos": "10",
        "Golos": "0",
        "Assistências": "-"
      },
      {
        "Época": "2023/24",
        "Equipa": "AFS",
        "Formação": "",
        "Jogos": "28",
        "Golos": "3",
        "Assistências": "1"
      }
    ],
    "Carreira no Farense": []
  },
  {
    "Nome": "Ryan Gauld",
    "ID": "223931",
    "Posição": "Médio",
    "Informações Pessoais": {
      "Nacionalidade": "EscóciaNaturalidadeAberdeenOutras LigaçõesPosiçãoMédio (Médio Ofensivo)Internacionalizações A6 Jogos / 0 GolosInt Jovens20 Jogos / 4 GolosPé preferencialEsquerdoAltura169 cmPeso64 kgSituaçãoNo ativoAgenteKey Sports Management Ltd.Clube atualVancouver WhitecapsHISTÓRICODFutebolÉPOCAEQUIPAJGAST2025Vancouver Whitecaps11332024Vancouver Whitecaps4117142023Vancouver Whitecaps421218+21 registosTRANSFERÊNCIASÉpocaEquipaValor2021Vancouver Whitecaps350 mil €2019/2020Farense-2018/2019Hibernian (emp)Custo zero2018/2019Farense (emp)Custo zero2017/2018Desp. Aves (emp)Custo zero2016/2017V. Setúbal (emp)Custo zero2014/2015Sporting2.75 M €RAIO XJogador",
      "Altura": "169 cmPeso64 kgSituaçãoNo ativoAgenteKey Sports Management Ltd.Clube atualVancouver WhitecapsHISTÓRICODFutebolÉPOCAEQUIPAJGAST2025Vancouver Whitecaps11332024Vancouver Whitecaps4117142023Vancouver Whitecaps421218+21 registosTRANSFERÊNCIASÉpocaEquipaValor2021Vancouver Whitecaps350 mil €2019/2020Farense-2018/2019Hibernian (emp)Custo zero2018/2019Farense (emp)Custo zero2017/2018Desp. Aves (emp)Custo zero2016/2017V. Setúbal (emp)Custo zero2014/2015Sporting2.75 M €RAIO XJogador"
    },
    "Carreira Completa": [
      {
        "Época": "2025",
        "Equipa": "Vancouver Whitecaps",
        "Formação": "",
        "Jogos": "11",
        "Golos": "3",
        "Assistências": "3"
      },
      {
        "Época": "2024",
        "Equipa": "Vancouver Whitecaps",
        "Formação": "",
        "Jogos": "41",
        "Golos": "17",
        "Assistências": "14"
      },
      {
        "Época": "2023",
        "Equipa": "Vancouver Whitecaps",
        "Formação": "",
        "Jogos": "42",
        "Golos": "12",
        "Assistências": "18"
      }
    ],
    "Carreira no Farense": []
  },
  {
    "Nome": "Amine Oudrhiri",
    "ID": "280505",
    "Posição": "Médio",
    "Informações Pessoais": {
      "Nacionalidade": "FrançaDupla NacionalidadeMarrocosNaturalidadeErmontOutras LigaçõesPosiçãoMédio (Médio Centro)Internacionalizações AInt JovensPé preferencialDireitoAltura184 cmPeso76 kgSituaçãoNo ativoAgenteMadeInFootballClube atualMaghreb FèsContrato2027/06HISTÓRICODFutebolÉPOCAEQUIPAJGAST2025/26Maghreb Fès50-2024/25Est. Amadora110-Rio Ave1500+21 registosTRANSFERÊNCIASÉpocaEquipaValor2025/2026Maghreb Fès-2024/2025Est. AmadoraCusto zero2021/2022Rio AveCusto zero2020/2021Farense-2017/2018Leixões-2016/2017Lusitano VRSA-2015/2016CS Sedan-2014/2015Arles-Avignon (emp)-2013/2014Nantes-2012/2013Red Star 93-RAIO XJogador",
      "Altura": "184 cmPeso76 kgSituaçãoNo ativoAgenteMadeInFootballClube atualMaghreb FèsContrato2027/06HISTÓRICODFutebolÉPOCAEQUIPAJGAST2025/26Maghreb Fès50-2024/25Est. Amadora110-Rio Ave1500+21 registosTRANSFERÊNCIASÉpocaEquipaValor2025/2026Maghreb Fès-2024/2025Est. AmadoraCusto zero2021/2022Rio AveCusto zero2020/2021Farense-2017/2018Leixões-2016/2017Lusitano VRSA-2015/2016CS Sedan-2014/2015Arles-Avignon (emp)-2013/2014Nantes-2012/2013Red Star 93-RAIO XJogador"
    },
    "Carreira Completa": [
      {
        "Época": "2025/26",
        "Equipa": "Maghreb Fès",
        "Formação": "",
        "Jogos": "5",
        "Golos": "0",
        "Assistências": "-"
      },
      {
        "Época": "2024/25",
        "Equipa": "Est. Amadora",
        "Formação": "",
        "Jogos": "11",
        "Golos": "0",
        "Assistências": "-"
      },
      {
        "Época": "",
        "Equipa": "Rio Ave",
        "Formação": "",
        "Jogos": "15",
        "Golos": "0",
        "Assistências": "0"
      }
    ],
    "Carreira no Farense": []
  },
  {
    "Nome": "Ângelo Taveira",
    "ID": "681348",
    "Posição": "Avançado",
    "Informações Pessoais": {
      "Nacionalidade": "PortugalDupla NacionalidadeAngolaNaturalidadeLagosOutras LigaçõesPosiçãoDefesa (Defesa Direito) / Avançado (Extremo Esquerdo)Internacionalizações AInt JovensPé preferencialDireitoAltura185 cmPeso79 kgSituaçãoNo ativoClube atualFK VarnsdorfHISTÓRICODFutebolÉPOCAEQUIPAJGAST2025/26FK Varnsdorf---2024/25SC Pombal231-2023/24U. Santarém61-+22 registosTRANSFERÊNCIASÉpocaEquipaValor2025/2026FK Varnsdorf-2024/2025Sp. Pombal-2023/2024U. Santarém-2023/2024Portimonense-2020/2021Louletano (emp)-2019/2020Louletano (emp)-2018/2019Farense-2013/2014Odiáxere-2012/2013Sport Lagos Benfica-RAIO XJogador",
      "Altura": "185 cmPeso79 kgSituaçãoNo ativoClube atualFK VarnsdorfHISTÓRICODFutebolÉPOCAEQUIPAJGAST2025/26FK Varnsdorf---2024/25SC Pombal231-2023/24U. Santarém61-+22 registosTRANSFERÊNCIASÉpocaEquipaValor2025/2026FK Varnsdorf-2024/2025Sp. Pombal-2023/2024U. Santarém-2023/2024Portimonense-2020/2021Louletano (emp)-2019/2020Louletano (emp)-2018/2019Farense-2013/2014Odiáxere-2012/2013Sport Lagos Benfica-RAIO XJogador"
    },
    "Carreira Completa": [
      {
        "Época": "2025/26",
        "Equipa": "FK Varnsdorf",
        "Formação": "",
        "Jogos": "-",
        "Golos": "-",
        "Assistências": "-"
      },
      {
        "Época": "2024/25",
        "Equipa": "SC Pombal",
        "Formação": "",
        "Jogos": "23",
        "Golos": "1",
        "Assistências": "-"
      },
      {
        "Época": "2023/24",
        "Equipa": "U. Santarém",
        "Formação": "",
        "Jogos": "6",
        "Golos": "1",
        "Assistências": "-"
      }
    ],
    "Carreira no Farense": []
  },
  {
    "Nome": "Madi Queta",
    "ID": "288913",
    "Posição": "Avançado",
    "Informações Pessoais": {
      "Nacionalidade": "Guiné-BissauDupla NacionalidadePortugalNaturalidadeBissauOutras LigaçõesPosiçãoAvançado (Extremo Esquerdo) / Avançado (Extremo Direito)Internacionalizações A4 Jogos / 0 GolosInt Jovens16 Jogos / 0 GolosPé preferencialDireitoAltura180 cmPeso66 kgEstreia como séniorEquipa:  FC PortoJogo: FC Porto 3-1 FC PenafielEdição: Ledman LigaPro 17/18Treinador: António FolhaÉpoca:  em 2017/18SituaçãoNo ativoClube atualFC PenafielContrato2027/06HISTÓRICODFutebolÉPOCAEQUIPAJGAST2025/26FC Penafiel40-2024/25Sebail PFK35312023/24Sebail PFK2001+19 registosEDIÇÕESEDIÇÃOJGASTEuro U19 2017200TRANSFERÊNCIASÉpocaEquipaValor2025/2026FC PenafielCusto zero2023/2024Sebail PFKCusto zero2023/2024CD MafraCusto zero2022/2023VilafranquenseCusto zero2022/2023Cherno MoreCusto zero2020/2021Farense-2013/2014Padroense (emp)-2011/2012FC Porto-RAIO XJogador",
      "Altura": "180 cmPeso66 kgEstreia como séniorEquipa:  FC PortoJogo: FC Porto 3-1 FC PenafielEdição: Ledman LigaPro 17/18Treinador: António FolhaÉpoca:  em 2017/18SituaçãoNo ativoClube atualFC PenafielContrato2027/06HISTÓRICODFutebolÉPOCAEQUIPAJGAST2025/26FC Penafiel40-2024/25Sebail PFK35312023/24Sebail PFK2001+19 registosEDIÇÕESEDIÇÃOJGASTEuro U19 2017200TRANSFERÊNCIASÉpocaEquipaValor2025/2026FC PenafielCusto zero2023/2024Sebail PFKCusto zero2023/2024CD MafraCusto zero2022/2023VilafranquenseCusto zero2022/2023Cherno MoreCusto zero2020/2021Farense-2013/2014Padroense (emp)-2011/2012FC Porto-RAIO XJogador"
    },
    "Carreira Completa": [
      {
        "Época": "2025/26",
        "Equipa": "FC Penafiel",
        "Formação": "",
        "Jogos": "4",
        "Golos": "0",
        "Assistências": "-"
      },
      {
        "Época": "2024/25",
        "Equipa": "Sebail PFK",
        "Formação": "",
        "Jogos": "35",
        "Golos": "3",
        "Assistências": "1"
      },
      {
        "Época": "2023/24",
        "Equipa": "Sebail PFK",
        "Formação": "",
        "Jogos": "20",
        "Golos": "0",
        "Assistências": "1"
      }
    ],
    "Carreira no Farense": []
  },
  {
    "Nome": "Djalma Campos",
    "ID": "33849",
    "Posição": "Avançado",
    "Informações Pessoais": {
      "Nacionalidade": "AngolaDupla NacionalidadePortugalNaturalidadeLuandaOutras LigaçõesParentescosFilho de Abel Campos, Irmão de Geovany Campos, Pai de Bryan Campos, Pai de Braune CamposPosiçãoAvançado (Extremo Direito) / Avançado (Extremo Esquerdo)Internacionalizações A49 Jogos / 8 GolosInt JovensPé preferencialDireitoAltura176 cmPeso80 kgSituaçãoRetirado das competições oficiaisClube atualSem EquipaHISTÓRICODFutebolÉPOCAEQUIPAJGAST2022/23Trofense24132021/22Trofense4012020/21Farense70-+31 registosFutebol de 6ÉPOCAEQUIPAJG2024/25FC Porto [Fut.6  Legends]--+31 registosEDIÇÕESEDIÇÃOJGASTCAN 2019310CAN 2013200CAN 2012300CAN 2010400TRANSFERÊNCIASÉpocaEquipaValor2024/2025FC Porto-2021/2022Trofense-2020/2021Farense-2018/2019Alanyaspor600 mil €2016/2017PAOK-2015/2016Gençlerbirligi-2014/2015Konyaspor (emp)-2013/2014Konyaspor (emp)500 mil €2012/2013Kasimpasa (emp)-2011/2012FC PortoCusto zero2006/2007Marítimo-2004/2005Alverca-HISTÓRICO COMO DIRIGENTEEquipasÉPOCAEQUIPASC ArcozeloVice-PresidenteRAIO XJogador",
      "Altura": "176 cmPeso80 kgSituaçãoRetirado das competições oficiaisClube atualSem EquipaHISTÓRICODFutebolÉPOCAEQUIPAJGAST2022/23Trofense24132021/22Trofense4012020/21Farense70-+31 registosFutebol de 6ÉPOCAEQUIPAJG2024/25FC Porto [Fut.6  Legends]--+31 registosEDIÇÕESEDIÇÃOJGASTCAN 2019310CAN 2013200CAN 2012300CAN 2010400TRANSFERÊNCIASÉpocaEquipaValor2024/2025FC Porto-2021/2022Trofense-2020/2021Farense-2018/2019Alanyaspor600 mil €2016/2017PAOK-2015/2016Gençlerbirligi-2014/2015Konyaspor (emp)-2013/2014Konyaspor (emp)500 mil €2012/2013Kasimpasa (emp)-2011/2012FC PortoCusto zero2006/2007Marítimo-2004/2005Alverca-HISTÓRICO COMO DIRIGENTEEquipasÉPOCAEQUIPASC ArcozeloVice-PresidenteRAIO XJogador"
    },
    "Carreira Completa": [
      {
        "Época": "2022/23",
        "Equipa": "Trofense",
        "Formação": "",
        "Jogos": "24",
        "Golos": "1",
        "Assistências": "3"
      },
      {
        "Época": "2021/22",
        "Equipa": "Trofense",
        "Formação": "",
        "Jogos": "4",
        "Golos": "0",
        "Assistências": "1"
      },
      {
        "Época": "2020/21",
        "Equipa": "Farense",
        "Formação": "",
        "Jogos": "7",
        "Golos": "0",
        "Assistências": "-"
      }
    ],
    "Carreira no Farense": [
      {
        "Época": "2020/21",
        "Equipa": "Farense",
        "Formação": "",
        "Jogos": "7",
        "Golos": "0",
        "Assistências": "-"
      }
    ]
  },
  {
    "Nome": "Nikola Stojiljkovic",
    "ID": "102404",
    "Posição": "Avançado",
    "Informações Pessoais": {
      "Nacionalidade": "SérviaNaturalidadeNisOutras LigaçõesPosiçãoAvançado (Ponta de Lança)Internacionalizações A4 Jogos / 0 GolosInt Jovens3 Jogos / 0 GolosPé preferencialDireitoAltura185 cmPeso80 kgSituaçãoRetirado das competições oficiaisAgenteGoodman SportsClube atualSem EquipaHISTÓRICODFutebolÉPOCAEQUIPAJGAST2023/24Hajer Club---Al-Kholood151-Dibba Al Fujairah10-+26 registosEDIÇÕESEDIÇÃOJGASTEuro U21 2015---TRANSFERÊNCIASÉpocaEquipaValor2023/2024Hajer Club-2023/2024Al Kholood-2023/2024Dibba Al Fujairah-2022/2023Al-Riyadh-2021/2022Piast GliwiceCusto zero2020/2021Farense-2019/2020Boavista (emp)-2018/2019Mallorca (emp)-2018/2019Crvena Zvezda (emp)200 mil €2017/2018Kayserispor (emp)500 mil €2015/2016SC Braga750 mil €2012/2013Cukaricki-RAIO XJogador",
      "Altura": "185 cmPeso80 kgSituaçãoRetirado das competições oficiaisAgenteGoodman SportsClube atualSem EquipaHISTÓRICODFutebolÉPOCAEQUIPAJGAST2023/24Hajer Club---Al-Kholood151-Dibba Al Fujairah10-+26 registosEDIÇÕESEDIÇÃOJGASTEuro U21 2015---TRANSFERÊNCIASÉpocaEquipaValor2023/2024Hajer Club-2023/2024Al Kholood-2023/2024Dibba Al Fujairah-2022/2023Al-Riyadh-2021/2022Piast GliwiceCusto zero2020/2021Farense-2019/2020Boavista (emp)-2018/2019Mallorca (emp)-2018/2019Crvena Zvezda (emp)200 mil €2017/2018Kayserispor (emp)500 mil €2015/2016SC Braga750 mil €2012/2013Cukaricki-RAIO XJogador"
    },
    "Carreira Completa": [
      {
        "Época": "2023/24",
        "Equipa": "Hajer Club",
        "Formação": "",
        "Jogos": "-",
        "Golos": "-",
        "Assistências": "-"
      },
      {
        "Época": "",
        "Equipa": "Al-Kholood",
        "Formação": "",
        "Jogos": "15",
        "Golos": "1",
        "Assistências": "-"
      },
      {
        "Época": "",
        "Equipa": "Dibba Al Fujairah",
        "Formação": "",
        "Jogos": "1",
        "Golos": "0",
        "Assistências": "-"
      }
    ],
    "Carreira no Farense": []
  },
  {
    "Nome": "Patrick Fernandes",
    "ID": "532769",
    "Posição": "Avançado",
    "Informações Pessoais": {
      "Nacionalidade": "Cabo VerdeNaturalidadePraiaOutras LigaçõesPosiçãoAvançado (Ponta de Lança) / Avançado (Extremo Direito)Internacionalizações A4 Jogos / 0 GolosInt JovensPé preferencialDireitoAltura190 cmPeso82 kgSituaçãoNo ativoAgenteMNM SportsClube atualFC OtelulHISTÓRICODFutebolÉPOCAEQUIPAJGAST2025/26FC Otelul14312024/25Marítimo31232023/24Torreense3765+15 registosTRANSFERÊNCIASÉpocaEquipaValor2025/2026FC Otelul-2024/2025MarítimoCusto zero2022/2023Torreense-2021/2022GD Chaves-2020/2021Varzim (emp)-2019/2020Farense-2018/2019Tondela-2017/2018FC Felgueiras 1932-2016/2017Oliv. Hospital-RAIO XJogador",
      "Altura": "190 cmPeso82 kgSituaçãoNo ativoAgenteMNM SportsClube atualFC OtelulHISTÓRICODFutebolÉPOCAEQUIPAJGAST2025/26FC Otelul14312024/25Marítimo31232023/24Torreense3765+15 registosTRANSFERÊNCIASÉpocaEquipaValor2025/2026FC Otelul-2024/2025MarítimoCusto zero2022/2023Torreense-2021/2022GD Chaves-2020/2021Varzim (emp)-2019/2020Farense-2018/2019Tondela-2017/2018FC Felgueiras 1932-2016/2017Oliv. Hospital-RAIO XJogador"
    },
    "Carreira Completa": [
      {
        "Época": "2025/26",
        "Equipa": "FC Otelul",
        "Formação": "",
        "Jogos": "14",
        "Golos": "3",
        "Assistências": "1"
      },
      {
        "Época": "2024/25",
        "Equipa": "Marítimo",
        "Formação": "",
        "Jogos": "31",
        "Golos": "2",
        "Assistências": "3"
      },
      {
        "Época": "2023/24",
        "Equipa": "Torreense",
        "Formação": "",
        "Jogos": "37",
        "Golos": "6",
        "Assistências": "5"
      }
    ],
    "Carreira no Farense": []
  },
  {
    "Nome": "Pedro Henrique",
    "ID": "507350",
    "Posição": "Avançado",
    "Informações Pessoais": {
      "Nacionalidade": "BrasilNaturalidadeGoiásOutras LigaçõesPosiçãoAvançado (Ponta de Lança)Internacionalizações AInt JovensPé preferencialDireitoAltura188 cmPeso80 kgSituaçãoNo ativoClube atualYunnan YukunHISTÓRICODFutebolÉPOCAEQUIPAJGAST2025Yunnan Yukun30115Khorfakkan72-2024Wuhan Three Towns22141+18 registosTRANSFERÊNCIASÉpocaEquipaValor2025Yunnan Yukun-2024/2025Khorfakkan1.40 M €2024Wuhan Three Towns900 mil €2023/2024Radomiak RadomCusto zero2020/2021Farense-2019/2020Feirense (emp)-2018/2019Benfica-2018/2019Leixões-2018Grêmio Anápolis-2017Atlético Goianiense (emp)-2017Grêmio Anápolis (emp)-RAIO XJogador",
      "Altura": "188 cmPeso80 kgSituaçãoNo ativoClube atualYunnan YukunHISTÓRICODFutebolÉPOCAEQUIPAJGAST2025Yunnan Yukun30115Khorfakkan72-2024Wuhan Three Towns22141+18 registosTRANSFERÊNCIASÉpocaEquipaValor2025Yunnan Yukun-2024/2025Khorfakkan1.40 M €2024Wuhan Three Towns900 mil €2023/2024Radomiak RadomCusto zero2020/2021Farense-2019/2020Feirense (emp)-2018/2019Benfica-2018/2019Leixões-2018Grêmio Anápolis-2017Atlético Goianiense (emp)-2017Grêmio Anápolis (emp)-RAIO XJogador"
    },
    "Carreira Completa": [
      {
        "Época": "2025",
        "Equipa": "Yunnan Yukun",
        "Formação": "",
        "Jogos": "30",
        "Golos": "11",
        "Assistências": "5"
      },
      {
        "Época": "",
        "Equipa": "Khorfakkan",
        "Formação": "",
        "Jogos": "7",
        "Golos": "2",
        "Assistências": "-"
      },
      {
        "Época": "2024",
        "Equipa": "Wuhan Three Towns",
        "Formação": "",
        "Jogos": "22",
        "Golos": "14",
        "Assistências": "1"
      }
    ],
    "Carreira no Farense": []
  },
  {
    "Nome": "Hugo Seco",
    "ID": "122601",
    "Posição": "Avançado",
    "Informações Pessoais": {
      "Nacionalidade": "PortugalNaturalidadeLousãOutras LigaçõesParentescosTio de Diego Francisco, Primo de André Seco, Pai de Dinis SecoPosiçãoAvançado (Extremo Esquerdo) / Avançado (Extremo Direito)Internacionalizações AInt JovensPé preferencialDireitoAltura176 cmPeso69 kgSituaçãoNo ativoAgenteNuno Patrão - Footis Lda.Clube atualU. LamasHISTÓRICODFutebolÉPOCAEQUIPAJGAST2025/26U. Lamas42-2024/25União 1919130-União 1919 [B]10-+33 registosTRANSFERÊNCIASÉpocaEquipaValor2025/2026U. Lamas-2024/2025União 1919-2021/2022Académica OAFCusto zero2019/2020FarenseCusto zero2018/2019Kisvárda-2018Irtysh-2016/2017Feirense-2016/2017Cherno MoreCusto zero2014/2015Académica-2013/2014Benf.C.Branco-2012/2013Fátima-2011/2012Benf.C.Branco-2010/2011St. Lawrence Spurs-2009/2010Ac. Viseu-2008/2009Nelas-2007/2008Anadia-2004/2005Académica-2003/2004Vigor Mocidade-2001/2002Académica-1999/2000Gândaras-RAIO XJogador",
      "Altura": "176 cmPeso69 kgSituaçãoNo ativoAgenteNuno Patrão - Footis Lda.Clube atualU. LamasHISTÓRICODFutebolÉPOCAEQUIPAJGAST2025/26U. Lamas42-2024/25União 1919130-União 1919 [B]10-+33 registosTRANSFERÊNCIASÉpocaEquipaValor2025/2026U. Lamas-2024/2025União 1919-2021/2022Académica OAFCusto zero2019/2020FarenseCusto zero2018/2019Kisvárda-2018Irtysh-2016/2017Feirense-2016/2017Cherno MoreCusto zero2014/2015Académica-2013/2014Benf.C.Branco-2012/2013Fátima-2011/2012Benf.C.Branco-2010/2011St. Lawrence Spurs-2009/2010Ac. Viseu-2008/2009Nelas-2007/2008Anadia-2004/2005Académica-2003/2004Vigor Mocidade-2001/2002Académica-1999/2000Gândaras-RAIO XJogador"
    },
    "Carreira Completa": [
      {
        "Época": "2025/26",
        "Equipa": "U. Lamas",
        "Formação": "",
        "Jogos": "4",
        "Golos": "2",
        "Assistências": "-"
      },
      {
        "Época": "2024/25",
        "Equipa": "União 1919",
        "Formação": "",
        "Jogos": "13",
        "Golos": "0",
        "Assistências": "-"
      },
      {
        "Época": "",
        "Equipa": "União 1919",
        "Formação": "",
        "Jogos": "1",
        "Golos": "0",
        "Assistências": "-"
      }
    ],
    "Carreira no Farense": []
  },
  {
    "Nome": "Brian Mansilla",
    "ID": "453674",
    "Posição": "Avançado",
    "Informações Pessoais": {
      "Nacionalidade": "ArgentinaNaturalidadeRosarioOutras LigaçõesPosiçãoAvançado (Extremo Esquerdo) / Avançado (Extremo Direito)Internacionalizações AInt Jovens12 Jogos / 2 GolosPé preferencialEsquerdoAltura178 cmPeso80 kgSituaçãoNo ativoAgenteProfuteClube atualAkhmat GroznyContrato2028/06HISTÓRICODFutebolÉPOCAEQUIPAJGAST2025/26Akhmat Grozny133-2024/25FK Orenburg29542023/24FK Orenburg3034+18 registosEDIÇÕESEDIÇÃOJGASTSudamericano U20 17920FIFA U20 WC 2017301TRANSFERÊNCIASÉpocaEquipaValor2025/2026Akhmat Grozny1.70 M €2022/2023FK Orenburg1.20 M €2021PlatenseCusto zero2020/2021Farense (emp)Custo zero2019/2020V. Setúbal (emp)Custo zero2019Gimnasia (emp)Custo zero2016Quilmes (emp)Custo zeroRAIO XJogador",
      "Altura": "178 cmPeso80 kgSituaçãoNo ativoAgenteProfuteClube atualAkhmat GroznyContrato2028/06HISTÓRICODFutebolÉPOCAEQUIPAJGAST2025/26Akhmat Grozny133-2024/25FK Orenburg29542023/24FK Orenburg3034+18 registosEDIÇÕESEDIÇÃOJGASTSudamericano U20 17920FIFA U20 WC 2017301TRANSFERÊNCIASÉpocaEquipaValor2025/2026Akhmat Grozny1.70 M €2022/2023FK Orenburg1.20 M €2021PlatenseCusto zero2020/2021Farense (emp)Custo zero2019/2020V. Setúbal (emp)Custo zero2019Gimnasia (emp)Custo zero2016Quilmes (emp)Custo zeroRAIO XJogador"
    },
    "Carreira Completa": [
      {
        "Época": "2025/26",
        "Equipa": "Akhmat Grozny",
        "Formação": "",
        "Jogos": "13",
        "Golos": "3",
        "Assistências": "-"
      },
      {
        "Época": "2024/25",
        "Equipa": "FK Orenburg",
        "Formação": "",
        "Jogos": "29",
        "Golos": "5",
        "Assistências": "4"
      },
      {
        "Época": "2023/24",
        "Equipa": "FK Orenburg",
        "Formação": "",
        "Jogos": "30",
        "Golos": "3",
        "Assistências": "4"
      }
    ],
    "Carreira no Farense": []
  },
  {
    "Nome": "Bilel Aouacheria",
    "ID": "416972",
    "Posição": "Avançado",
    "Informações Pessoais": {
      "Nacionalidade": "FrançaDupla NacionalidadeArgéliaNaturalidadeSaint-ÉtienneOutras LigaçõesPosiçãoAvançado (Extremo Esquerdo) / Avançado (2.º avançado)Internacionalizações AInt JovensPé preferencialDireitoAltura180 cmPeso77 kgSituaçãoNo ativoClube atualSem EquipaHISTÓRICODFutebolÉPOCAEQUIPAJGAST2024/25Al-Najma167-2023/24FK Qabala37612022/23Gil Vicente2912+18 registosTRANSFERÊNCIASÉpocaEquipaValor2024/2025Al-Najma-2023/2024FK QabalaCusto zero2021/2022Gil Vicente-2020/2021Farense-2017/2018Moreirense-2016/2017Sporting (emp)-2014/2015Sp. Covilhã-RAIO XJogador",
      "Altura": "180 cmPeso77 kgSituaçãoNo ativoClube atualSem EquipaHISTÓRICODFutebolÉPOCAEQUIPAJGAST2024/25Al-Najma167-2023/24FK Qabala37612022/23Gil Vicente2912+18 registosTRANSFERÊNCIASÉpocaEquipaValor2024/2025Al-Najma-2023/2024FK QabalaCusto zero2021/2022Gil Vicente-2020/2021Farense-2017/2018Moreirense-2016/2017Sporting (emp)-2014/2015Sp. Covilhã-RAIO XJogador"
    },
    "Carreira Completa": [
      {
        "Época": "2024/25",
        "Equipa": "Al-Najma",
        "Formação": "",
        "Jogos": "16",
        "Golos": "7",
        "Assistências": "-"
      },
      {
        "Época": "2023/24",
        "Equipa": "FK Qabala",
        "Formação": "",
        "Jogos": "37",
        "Golos": "6",
        "Assistências": "1"
      },
      {
        "Época": "2022/23",
        "Equipa": "Gil Vicente",
        "Formação": "",
        "Jogos": "29",
        "Golos": "1",
        "Assistências": "2"
      }
    ],
    "Carreira no Farense": []
  },
  {
    "Nome": "Alvarinho",
    "ID": "146058",
    "Posição": "Avançado",
    "Informações Pessoais": {
      "Nacionalidade": "PortugalDupla NacionalidadeAngolaNaturalidadeFaroOutras LigaçõesPosiçãoAvançado (Extremo Direito) / Avançado (2.º avançado)Internacionalizações AInt JovensPé preferencialEsquerdoAltura170 cmPeso62 kgSituaçãoRetirado das competições oficiaisAgenteNewrofootClube atualSem EquipaHISTÓRICODFutebolÉPOCAEQUIPAJGAST2024/25Moncarapachense32762023/24Anadia FC27722022/23Ethnikos Achnas2431+30 registosTRANSFERÊNCIASÉpocaEquipaValor2024/2025Moncarapachense-2023/2024Anadia FC-2022/2023Ethnikos Achnas-2021/2022Louletano-2017/2018Farense-2016/2017Slask Wroclaw (emp)-2016/2017Slask Wroclaw (emp)-2015/2016Jagiellonia Bialystok-2013/2014Zawisza Bydgoszcz-2012/2013Benf.C.Branco-2011/2012Torreense (emp)-2011/2012Fátima (emp)-2010/2011P. Ferreira-HISTÓRICO COMO TREINADOREquipasÉPOCAEQUIPAJV2025/26FarenseCoordenador de Scouting--+2 registosRAIO XJogador",
      "Altura": "170 cmPeso62 kgSituaçãoRetirado das competições oficiaisAgenteNewrofootClube atualSem EquipaHISTÓRICODFutebolÉPOCAEQUIPAJGAST2024/25Moncarapachense32762023/24Anadia FC27722022/23Ethnikos Achnas2431+30 registosTRANSFERÊNCIASÉpocaEquipaValor2024/2025Moncarapachense-2023/2024Anadia FC-2022/2023Ethnikos Achnas-2021/2022Louletano-2017/2018Farense-2016/2017Slask Wroclaw (emp)-2016/2017Slask Wroclaw (emp)-2015/2016Jagiellonia Bialystok-2013/2014Zawisza Bydgoszcz-2012/2013Benf.C.Branco-2011/2012Torreense (emp)-2011/2012Fátima (emp)-2010/2011P. Ferreira-HISTÓRICO COMO TREINADOREquipasÉPOCAEQUIPAJV2025/26FarenseCoordenador de Scouting--+2 registosRAIO XJogador"
    },
    "Carreira Completa": [
      {
        "Época": "2024/25",
        "Equipa": "Moncarapachense",
        "Formação": "",
        "Jogos": "32",
        "Golos": "7",
        "Assistências": "6"
      },
      {
        "Época": "2023/24",
        "Equipa": "Anadia FC",
        "Formação": "",
        "Jogos": "27",
        "Golos": "7",
        "Assistências": "2"
      },
      {
        "Época": "2022/23",
        "Equipa": "Ethnikos Achnas",
        "Formação": "",
        "Jogos": "24",
        "Golos": "3",
        "Assistências": "1"
      }
    ],
    "Carreira no Farense": []
  },
  {
    "Nome": "Licá",
    "ID": "35255",
    "Posição": "Avançado",
    "Informações Pessoais": {
      "Nacionalidade": "PortugalNaturalidadeLamelasOutras LigaçõesParentescosIrmão de PJPosiçãoAvançado (Extremo Esquerdo) / Avançado (2.º avançado)Internacionalizações A1 Jogos / 0 GolosInt Jovens5 Jogos / 1 GolosPé preferencialDireitoAltura181 cmPeso69 kgSituaçãoNo ativoClube atualACDR LamelasHISTÓRICODFutebolÉPOCAEQUIPAJGAST2025/26ACDR Lamelas51-2024/25ACDR Lamelas3235-2023/24ACDR Lamelas258-+31 registosFutebol de 6ÉPOCAEQUIPAJG2024/25Estoril Praia [Fut.6  Legends]--+31 registosTRANSFERÊNCIASÉpocaEquipaValor2024/2025ACDR Lamelas-2024/2025Estoril Praia-2022/2023ACDR Lamelas-2021/2022Belenenses SAD-2020/2021Farense-2018/2019Belenenses SAD-2017/2018Belenenses-2017/2018GranadaCusto zero2016/2017Estoril Praia (emp)-2016/2017Nottingham Forest358 mil €2015/2016Vitória SC (emp)-2014/2015Rayo Vallecano (emp)-2013/2014FC Porto1.50 M €2011/2012Estoril PraiaCusto zero2010/2011Trofense (emp)-2009/2010Trofense (emp)-2009/2010Académica OAF-2008/2009Tourizense-2008/2009Académica-2007/2008Tourizense-2006/2007Social Lamas-RAIO XJogador",
      "Altura": "181 cmPeso69 kgSituaçãoNo ativoClube atualACDR LamelasHISTÓRICODFutebolÉPOCAEQUIPAJGAST2025/26ACDR Lamelas51-2024/25ACDR Lamelas3235-2023/24ACDR Lamelas258-+31 registosFutebol de 6ÉPOCAEQUIPAJG2024/25Estoril Praia [Fut.6  Legends]--+31 registosTRANSFERÊNCIASÉpocaEquipaValor2024/2025ACDR Lamelas-2024/2025Estoril Praia-2022/2023ACDR Lamelas-2021/2022Belenenses SAD-2020/2021Farense-2018/2019Belenenses SAD-2017/2018Belenenses-2017/2018GranadaCusto zero2016/2017Estoril Praia (emp)-2016/2017Nottingham Forest358 mil €2015/2016Vitória SC (emp)-2014/2015Rayo Vallecano (emp)-2013/2014FC Porto1.50 M €2011/2012Estoril PraiaCusto zero2010/2011Trofense (emp)-2009/2010Trofense (emp)-2009/2010Académica OAF-2008/2009Tourizense-2008/2009Académica-2007/2008Tourizense-2006/2007Social Lamas-RAIO XJogador"
    },
    "Carreira Completa": [
      {
        "Época": "2025/26",
        "Equipa": "ACDR Lamelas",
        "Formação": "",
        "Jogos": "5",
        "Golos": "1",
        "Assistências": "-"
      },
      {
        "Época": "2024/25",
        "Equipa": "ACDR Lamelas",
        "Formação": "",
        "Jogos": "32",
        "Golos": "35",
        "Assistências": "-"
      },
      {
        "Época": "2023/24",
        "Equipa": "ACDR Lamelas",
        "Formação": "",
        "Jogos": "25",
        "Golos": "8",
        "Assistências": "-"
      }
    ],
    "Carreira no Farense": []
  }
]